NeoInvestSDK/__init__.py
NeoInvestSDK/py.typed
NeoInvestSDK/api/__init__.py
NeoInvestSDK/api/account_api.py
NeoInvestSDK/api/asset_api.py
NeoInvestSDK/api/authentication_api.py
NeoInvestSDK/api/client.py
NeoInvestSDK/api/market_data_api.py
NeoInvestSDK/api/trading_api.py
NeoInvestSDK/api/models/__init__.py
NeoInvestSDK/api/models/account_models.py
NeoInvestSDK/api/models/authentication_models.py
NeoInvestSDK/api/models/common.py
NeoInvestSDK/api/models/market_data_models.py
NeoInvestSDK/api/models/order_models.py
NeoInvestSDK/api/models/portfolio_models.py
NeoInvestSDK/common/__init__.py
NeoInvestSDK/common/config.py
NeoInvestSDK/common/constants.py
NeoInvestSDK/common/exceptions.py
NeoInvestSDK/common/mapper.py
NeoInvestSDK/common/schema_mapping.py
NeoInvestSDK/stock_stream/__init__.py
NeoInvestSDK/stock_stream/client.py
NeoInvestSDK/stock_stream/models/__init__.py
NeoInvestSDK/stock_stream/models/fu_top_n_price.py
NeoInvestSDK/stock_stream/models/market_data.py
NeoInvestSDK/stock_stream/models/market_info.py
NeoInvestSDK/stock_stream/models/market_session.py
NeoInvestSDK/stock_stream/models/market_volume.py
NeoInvestSDK/stock_stream/models/stock_info.py
NeoInvestSDK/stock_stream/models/ws_message.py
NeoInvestSDK/trading_stream/__init__.py
NeoInvestSDK/trading_stream/client.py
NeoInvestSDK/trading_stream/models/__init__.py
NeoInvestSDK/trading_stream/models/cash_notification.py
NeoInvestSDK/trading_stream/models/order_status.py
NeoInvestSDK/trading_stream/models/trading_message.py
neoinvestsdk-0.2.5.dist-info/METADATA
neoinvestsdk-0.2.5.dist-info/WHEEL
neoinvestsdk-0.2.5.dist-info/top_level.txt
neoinvestsdk-0.2.5.dist-info/RECORD
